{
  "certificate": {
    "id": "2020-024",
    "url": "https://codecheck.org.uk/register/certs/2020-024/"
  },
  "paper": {
    "title": "Driftage: a multi-agent system framework for concept drift detection\n",
    "authors": [
      {
        "name": "Diogo Munaro Vieira"
      },
      {
        "name": "Chrystinne Fernandes"
      },
      {
        "name": "Carlos Lucena"
      },
      {
        "name": "Sérgio Lifschitz",
        "orcid": "0000-0003-3073-3734"
      }
    ],
    "reference": "https://doi.org/10.1093/gigascience/giab030",
    "abstract": {
      "text": "We conclude that using Driftage, arises a new paradigm to implement concept drift algorithms with multi-agent architecture that contributes to split drift detection responsability, algorithms interpretability and more dynamic algorithms adaptation.",
      "source": "OpenAlex"
    },
    "openalex": "https://openalex.org/W3165405739"
  },
  "codecheck": {
    "codecheckers": [
      {
        "name": "Stephen J. Eglen",
        "orcid": "0000-0001-8607-8025"
      }
    ],
    "check_time": "2020-12-07 15:00:00",
    "repository": "github::codecheckers/driftage",
    "report": "https://doi.org/10.5281/zenodo.4964880",
    "type": "journal",
    "venue": "GigaScience",
    "summary": "Reproduction from mybinder\n",
    "manifest": [
      {
        "file": "driftage_download.png",
        "comment": "manuscript Figure 5 (bottom two rows only)"
      }
    ]
  }
}
